{
  "project_info": {
    "project_number": "912570771299",
    "project_id": "filmscape-ce474",
    "storage_bucket": "filmscape-ce474.firebasestorage.app"
  },
  "client": [
    {
      "client_info": {
        "mobilesdk_app_id": "1:912570771299:android:d51494a154bfd0917d5556",
        "android_client_info": {
          "package_name": "com.furkanhrmnc.filmscape"
        }
      },
      "oauth_client": [],
      "api_key": [
        {
          "current_key": "AIzaSyCarpMYPMJ6RUA5-_TkKYoRKuMvvrqpCoM"
        }
      ],
      "services": {
        "appinvite_service": {
          "other_platform_oauth_client": []
        }
      }
    }
  ],
  "configuration_version": "1"
}